cqbot/__init__.py
cqbot/action.py
cqbot/bot.py
cqbot/cmd.py
cqbot/cq.py
cqbot/enum.py
cqbot/event.py
cqbot-0.0.7.dist-info/LICENSE
cqbot-0.0.7.dist-info/METADATA
cqbot-0.0.7.dist-info/WHEEL
cqbot-0.0.7.dist-info/top_level.txt
cqbot-0.0.7.dist-info/RECORD
