Metadata-Version: 2.1
Name: cqbot
Version: 0.0.7
Summary: go-cqhttp python 框架，可以用于快速塔建 bot
Home-page: https://github.com/lhlyu/cqbot
Author: lhlyu
License: MIT
Platform: any
Classifier: Programming Language :: Python :: 3
Classifier: Operating System :: OS Independent
Requires-Python: >=3.10
License-File: LICENSE
Requires-Dist: requests
Requires-Dist: pyyaml
Requires-Dist: websocket-client
